oxfel/__init__.py
oxfel/accelerator/__init__.py
oxfel/accelerator/lattice/__init__.py
oxfel/accelerator/lattice/b1d-real-optics.pcl
oxfel/accelerator/lattice/b1d.py
oxfel/accelerator/lattice/b2d-real-optics.pcl
oxfel/accelerator/lattice/b2d.py
oxfel/accelerator/lattice/cl.py
oxfel/accelerator/lattice/component_list_2023.07.01.xls
oxfel/accelerator/lattice/conversion-config.toml
oxfel/accelerator/lattice/i1.py
oxfel/accelerator/lattice/i1d-real-optics.pcl
oxfel/accelerator/lattice/i1d.py
oxfel/accelerator/lattice/l1.py
oxfel/accelerator/lattice/l2.py
oxfel/accelerator/lattice/l3.py
oxfel/accelerator/lattice/real-linear-config.toml
oxfel/accelerator/lattice/real-matched-conf.toml
oxfel/accelerator/lattice/sa2.py
oxfel/accelerator/lattice/t1.py
oxfel/accelerator/lattice/t3.py
oxfel/accelerator/lattice/t5.py
oxfel/accelerator/lattice/t5d.py
oxfel/accelerator/lattice/tl1tl2.py
oxfel/accelerator/lattice/tl3tl4.py
oxfel/accelerator/lattice/tl5.py
oxfel/accelerator/lattice/tld-real-optics.pcl
oxfel/accelerator/lattice/tld.py
oxfel/accelerator/lattice/tracking-matched-conf.toml
oxfel/accelerator/sections.py
oxfel/astra/BSA1d_3ps_250pC_10k.ini
oxfel/astra/Main_and_Buck_sym2.prn
oxfel/astra/__init__.py
oxfel/astra/converter.py
oxfel/astra/euxfel-injector-100k.0320.001.gz
oxfel/astra/euxfel-injector.in
oxfel/astra/load.py
oxfel/astra/rz_GUN_FEM-003-531-531-filt3.dat
oxfel/astra/tesla1cav2.dat
oxfel/astra/tesla4cav3.dat
oxfel/cli.py
oxfel/conversion.py
oxfel/defaultprocs.py
oxfel/fel_track.py
oxfel/longlist.py
oxfel/matching.py
oxfel/optics.py
oxfel/plot.py
oxfel/predefined.py
oxfel/processes.py
oxfel/processes.yaml
oxfel/py.typed
oxfel/secmatch.py
oxfel/sequence.py
oxfel/tracking.py
oxfel/wakes/__init__.py
oxfel/wakes/dechirper/IntegrTr.m
oxfel/wakes/dechirper/PP_WakeZY_analytical4ECHO.m
oxfel/wakes/dechirper/PP_WakeZY_analytical4ECHO1.m
oxfel/wakes/dechirper/PP_WakeZY_analytical4ECHO_old.m
oxfel/wakes/dechirper/__init__.py
oxfel/wakes/dechirper/test.py
oxfel-0.5.0.dist-info/AUTHORS.rst
oxfel-0.5.0.dist-info/LICENSE
oxfel-0.5.0.dist-info/METADATA
oxfel-0.5.0.dist-info/WHEEL
oxfel-0.5.0.dist-info/entry_points.txt
oxfel-0.5.0.dist-info/RECORD
