Metadata-Version: 2.1
Name: oxfel
Version: 0.5.0
Summary: The official UNOFFICIAL model of the EuXFEL in OCELOT
Home-page: https://github.com/st-walker/esmesim
License: MIT
Author: Stuart Walker
Author-email: stuart.walker@desy.de
Requires-Python: >=3.10.11,<4.0
Classifier: Development Status :: 2 - Pre-Alpha
Classifier: Intended Audience :: Developers
Classifier: License :: OSI Approved :: MIT License
Classifier: Natural Language :: English
Classifier: Programming Language :: Python :: 3
Classifier: Programming Language :: Python :: 3.11
Classifier: Programming Language :: Python :: 3.12
Classifier: Programming Language :: Python :: 3.9
Requires-Dist: click (>=8.1.7,<9.0.0)
Requires-Dist: latdraw (>=0.1.1a0,<0.2.0)
Requires-Dist: matplotlib (>=3.7.1,<4.0.0)
Requires-Dist: numpy (>=1.24.3,<2.0)
Requires-Dist: ocelot-desy (>=24.3.0,<25.0.0)
Requires-Dist: pandas (>=2.0.2,<3.0.0)
Requires-Dist: pyyaml (>=6.0.1,<7.0.0)
Requires-Dist: toml (>=0.10.2,<0.11.0)
Requires-Dist: xlrd (>=2.0.1,<3.0.0)
